.gitignore
COPYING
MANIFEST.in
README.rst
requirements.txt
setup.py
test-requirements.txt
tox.ini
framer/__init__.py
framer/exc.py
framer/framers.py
framer/protocol.py
framer/transport.py
framer.egg-info/PKG-INFO
framer.egg-info/SOURCES.txt
framer.egg-info/dependency_links.txt
framer.egg-info/pbr.json
framer.egg-info/requires.txt
framer.egg-info/top_level.txt
tests/__init__.py
tests/unit/__init__.py
tests/unit/test_framers.py
tests/unit/test_transport.py