Metadata-Version: 1.1
Name: framer
Version: 0.1.1
Summary: Network Framer Library
Home-page: https://github.com/klmitch/framer
Author: Kevin L. Mitchell
Author-email: klmitch@mit.edu
License: UNKNOWN
Platform: UNKNOWN
Classifier: Development Status :: 3 - Alpha
Classifier: Intended Audience :: Developers
Classifier: License :: OSI Approved :: GNU General Public License (GPL)
Classifier: Operating System :: OS Independent
Classifier: Programming Language :: Python
Classifier: Programming Language :: Python :: 2.7
Classifier: Programming Language :: Python :: 3.3
Classifier: Programming Language :: Python :: 3.4
